risk_mgmt/VaR.py
risk_mgmt/__init__.py
risk_mgmt/calculation.py
risk_mgmt/cov_matrix.py
risk_mgmt/linear_regression.py
risk_mgmt/simulation.py
risk_mgmt-0.4.0.dist-info/METADATA
risk_mgmt-0.4.0.dist-info/WHEEL
risk_mgmt-0.4.0.dist-info/top_level.txt
risk_mgmt-0.4.0.dist-info/RECORD
