Metadata-Version: 2.1
Name: risk-mgmt
Version: 0.4.0
Summary: using for quatitative risk management
Author: Qihang Ma
Requires-Dist: pandas
Requires-Dist: numpy
